LICENSE
MANIFEST.in
README.md
setup.py
django_onthefly.egg-info/PKG-INFO
django_onthefly.egg-info/SOURCES.txt
django_onthefly.egg-info/dependency_links.txt
django_onthefly.egg-info/requires.txt
django_onthefly.egg-info/top_level.txt
onthefly/__init__.py
onthefly/admin.py
onthefly/apps.py
onthefly/monkey_patch.py
onthefly/utils.py
onthefly/backend/__init__.py
onthefly/backend/redis_backend.py
onthefly/backend/twelvefactor_backend.py
onthefly/templates/admin/onthefly_settings.html
onthefly/templatetags/__init__.py
onthefly/templatetags/onthefly.py