Metadata-Version: 1.1
Name: django-onthefly
Version: 0.1.9
Summary: Change Django Settings On the Fly
Home-page: https://github.com/baranbartu/onthefly
Author: Baran Bartu Demirci
Author-email: bbartu.demirci@gmail.com
License: MIT
Download-URL: https://github.com/baranbartu/onthefly/tarball/0.1.9
Keywords: django,settings,change django settings
Platform: UNKNOWN
